{"info":{"_postman_id":"c27b98fb-bf01-41c6-9f4e-6a9da0ea5053","name":"Books","schema":"https://schema.getpostman.com/json/collection/v2.1.0/collection.json"},"item":[{"name":"GetBooks","id":"2c513701-ff20-4423-8e42-8d023c82c813","protocolProfileBehavior":{"disableBodyPruning":true},"request":{"method":"GET","header":[],"url":{"raw":"{{url}}/Books","host":["{{url}}"],"path":["Books"]}},"response":[]},{"name":"GetBook","id":"0475714c-d830-428e-b5bd-33a3889780d3","protocolProfileBehavior":{"disableBodyPruning":true},"request":{"method":"GET","header":[],"url":{"raw":"{{url}}/Books/1","host":["{{url}}"],"path":["Books","1"]}},"response":[]},{"name":"CreateBook","id":"e18570a7-367e-4711-8ba4-6d7abc9a31b2","protocolProfileBehavior":{"disableBodyPruning":true},"request":{"method":"POST","header":[],"body":{"mode":"raw","raw":"{\n    \"title\": \"Don Quijote\",\n    \"pages\": 20,\n    \"language\": \"English\",\n    \"publicationDate\": \"2012-02-20T00:00:00\",\n    \"description\": \"A la pregunta de cuál es el libro más importante escrito en su lengua, cualquier hablante de español responderá sin duda que Don Quijote de la Mancha, de Miguel de Cervantes. Aunque, si la pregunta es si se ha leído entero, entonces no todo el mundo dirá que sí. A continuación, te presentamos un resumen de este magnífico libro para que te animes a leerlo.\",\n    \"status\": \"Active\",\n    \"authorId\": 1,\n    \"editorialId\": 1\n}","options":{"raw":{"language":"json"}}},"url":{"raw":"{{url}}/Books/Create","host":["{{url}}"],"path":["Books","Create"]}},"response":[]},{"name":"UpdateBook","id":"538751d6-a79d-4a61-9be8-93b0be51be03","protocolProfileBehavior":{"disableBodyPruning":true},"request":{"method":"PUT","header":[],"body":{"mode":"raw","raw":"{\n\t\"id\": 2,\n\t\"title\": \"asi hablo zaratustra\",\n\t\"pages\": 20,\n\t\"language\": \"Español\",\n\t\"publicationDate\": \"2012-02-20T00:00:00\",\n\t\"description\": \"Zoroastro o Zarathustra, castellanizado Zaratustra, o también Zarathushtra Spitama o Ashu Zarathushtra, fue un antiguo profeta y filósofo iraní que fundó lo que ahora se conoce como zoroastrismo\",\n\t\"status\": \"Active\",\n\t\"authorId\": 1,\n\t\"author\": null,\n\t\"editorialId\": 1,\n\t\"editorial\": null\n}","options":{"raw":{"language":"json"}}},"url":{"raw":"{{url}}/Books/Update/2","host":["{{url}}"],"path":["Books","Update","2"]}},"response":[]},{"name":"InactiveBook","id":"ff42b916-eb54-4eb0-80c7-bdf5878e9396","protocolProfileBehavior":{"disableBodyPruning":true},"request":{"method":"PUT","header":[],"url":{"raw":"{{url}}/Books/Inactive/2","host":["{{url}}"],"path":["Books","Inactive","2"]}},"response":[]},{"name":"ActiveBook","id":"757f8e8f-6145-4ff7-a140-639f743ebfed","protocolProfileBehavior":{"disableBodyPruning":true},"request":{"method":"PUT","header":[],"url":{"raw":"{{url}}/Books/Active/2","host":["{{url}}"],"path":["Books","Active","2"]}},"response":[]}]}